eventmapper/__init__.py
eventmapper/version.py
panda3d_eventmapper-0.3.0.dist-info/LICENSE.txt
panda3d_eventmapper-0.3.0.dist-info/METADATA
panda3d_eventmapper-0.3.0.dist-info/WHEEL
panda3d_eventmapper-0.3.0.dist-info/top_level.txt
panda3d_eventmapper-0.3.0.dist-info/RECORD
