Metadata-Version: 2.1
Name: panda3d-eventmapper
Version: 0.3.0
Summary: Simple utility to remap Panda3D events
Home-page: https://github.com/Moguri/panda3d-eventmapper
Author: Mitchell Stokes
License: BSD
Project-URL: Bug Tracker, https://github.com/Moguri/panda3d-eventmapper/issues
Keywords: panda3d,gamedev
Platform: UNKNOWN
Classifier: Development Status :: 4 - Beta
Classifier: License :: OSI Approved :: BSD License
Classifier: Programming Language :: Python :: 3
Requires-Python: >=3.6
License-File: LICENSE.txt
Requires-Dist: panda3d
Provides-Extra: test
Requires-Dist: pytest ; extra == 'test'
Requires-Dist: pylint (==2.4.*) ; extra == 'test'
Requires-Dist: pytest-pylint ; extra == 'test'
